{
  "propertyName": "Luxury Beachfront Resort",
  "clientName": "João Silva",
  "address": "Praia de Taperapuan, Porto Seguro, CEP 45810-000, Brazil",
  "rating": 8.9,
  "reviewCount": 1245,
  "checkInDate": "2026-02-13",
  "checkOutDate": "2026-02-17",
  "hospedageValue": 2198,
  "paymentLink100": null,
  "paymentLink30Pix": null,
  "depositPercentage": 16,
  "clientEmail": "hospede@booking.example.com",
  "clientPhone": "+55 (11) 99999-9999",
  "clientCpf": null,
  "guestCount": 2,
  "detail1": "Não reembolsvel",
  "detail2": "WiFi disponível",
  "detail3": "Café da manhã incluido",
  "roomType": "Quarto Duplo",
  "breakfastIncluded": 1,
  "freeCancellationDate": "2026-01-29",
  "mainGuestName": "Wallas Pereira",
  "photos": "[{\"id\":\"1\",\"url\":\"/images/hotel-hero.jpg\",\"title\":\"Hotel Exterior\"},{\"id\":\"2\",\"url\":\"/images/hotel-room.jpg\",\"title\":\"Hotel Room\"},{\"id\":\"3\",\"url\":\"/images/hotel-pool.jpg\",\"title\":\"Pool Area\"}]"
}
